udeploy/__init__.py
udeploy/__main__.py
udeploy-0.0.4.dist-info/LICENSE
udeploy-0.0.4.dist-info/METADATA
udeploy-0.0.4.dist-info/WHEEL
udeploy-0.0.4.dist-info/entry_points.txt
udeploy-0.0.4.dist-info/top_level.txt
udeploy-0.0.4.dist-info/RECORD
