Metadata-Version: 2.1
Name: udeploy
Version: 0.0.4
Summary: Простой скрипт на питоне, который поможет развернуть ваше приложение
Home-page: https://github.com/ogurechik/udeploy
Author: Oleg Silver
Author-email: rav-navini-gego-cutropal@yandex.ru
License: MIT
Platform: UNKNOWN
Classifier: Programming Language :: Python :: 3
Classifier: License :: OSI Approved :: MIT License
Classifier: Operating System :: POSIX :: Linux
Requires-Python: >=3.6
